ngehtutil/__init__.py
ngehtutil/array.py
ngehtutil/campaign.py
ngehtutil/program.py
ngehtutil/source.py
ngehtutil/station.py
ngehtutil/station_weather.py
ngehtutil/target.py
ngehtutil/version.py
ngehtutil/config/arrays.csv
ngehtutil/config/sources.csv
ngehtutil/config/targets.csv
ngehtutil/config/telescope_sites.xlsx
ngehtutil/cost/README.md
ngehtutil/cost/__init__.py
ngehtutil/cost/cost_config.py
ngehtutil/cost/cost_constants.xlsx
ngehtutil/cost/cost_model.py
ngehtutil/cost/cost_timing.py
ngehtutil/cost/examples/README.txt
ngehtutil/cost/examples/array_setup.xlsx
ngehtutil/cost/examples/cost.py
ngehtutil/cost/examples/exercise.py
ngehtutil/cost/examples/exercise_vis.py
ngehtutil/cost/examples/site_info.xlsx
ngehtutil/images/Einstein.png
ngehtutil/images/Einstein2.png
ngehtutil/images/GRRT_IMAGE_data1400_freq230.npy
ngehtutil/images/GRRT_IMAGE_data1400_freq345.npy
ngehtutil/images/M87_230.png
ngehtutil/images/M87_345.png
ngehtutil/images/SGRA_230.png
ngehtutil/images/SGRA_345.png
ngehtutil/images/fromm230_scat.npy
ngehtutil/images/fromm345_scat.npy
ngehtutil/images/quickstart_M87_230.png
ngehtutil/images/quickstart_M87_345.png
ngehtutil/images/quickstart_SGRA_230.png
ngehtutil/images/quickstart_SGRA_345.png
ngehtutil/images/riaf_freq_2.3e+11_0003.npy
ngehtutil/images/riaf_freq_2.3e+11_0003.png
ngehtutil/images/riaf_freq_2.3e+11_0006.npy
ngehtutil/images/riaf_freq_2.3e+11_0006.png
ngehtutil/images/riaf_freq_3.45e+11_0003.npy
ngehtutil/images/riaf_freq_3.45e+11_0003.png
ngehtutil/images/riaf_freq_3.45e+11_0006.npy
ngehtutil/images/riaf_freq_3.45e+11_0006.png
ngehtutil/images/riaf_freq_4.5e+11_0003.npy
ngehtutil/images/riaf_freq_4.5e+11_0003.png
ngehtutil/images/riaf_freq_4.5e+11_0006.npy
ngehtutil/images/riaf_freq_4.5e+11_0006.png
ngehtutil/images/riaf_freq_6.9e+11_0003.npy
ngehtutil/images/riaf_freq_6.9e+11_0003.png
ngehtutil/images/riaf_freq_6.9e+11_0006.npy
ngehtutil/images/riaf_freq_6.9e+11_0006.png
ngehtutil/images/riaf_freq_8.6e+10_0003.npy
ngehtutil-1.0.21.dist-info/METADATA
ngehtutil-1.0.21.dist-info/WHEEL
ngehtutil-1.0.21.dist-info/licenses/LICENSE
ngehtutil-1.0.21.dist-info/licenses/LICENSE.BSD-3-Clause
ngehtutil-1.0.21.dist-info/licenses/LICENSE.CFA
ngehtutil-1.0.21.dist-info/RECORD
