Metadata-Version: 2.1
Name: ngehtutil
Version: 1.0.21
Summary: A set of utilities for describing VLBI arrays, stations, costs, weather, etc.
Project-URL: Homepage, https://github.com/Smithsonian/ngehtutil
Project-URL: Bug Tracker, https://github.com/Smithsonian/ngehtutil/issues
Author-email: Aaron Oppenheimer <aaron.oppenheimer@cfa.harvard.edu>, Mark Freeman <mfreeman@cfa.harvard.edu>
License: Copyright (c) 2022 Center for Astrophysics | Harvard & Smithsonian
License-File: LICENSE
License-File: LICENSE.BSD-3-Clause
License-File: LICENSE.CFA
Classifier: License :: OSI Approved :: BSD License
Classifier: Operating System :: OS Independent
Classifier: Programming Language :: Python :: 3
Requires-Python: >=3.7
Requires-Dist: ehtim>=1.2.3
Requires-Dist: jupyter-console>=6.4.3
Requires-Dist: openpyxl>=3.0.9
Requires-Dist: pandas>=1.4.1
Requires-Dist: pillow>=9.0.1
Requires-Dist: requests>=2.27.1
